uvicorn_hmr-0.1.1.8.dist-info/METADATA
uvicorn_hmr-0.1.1.8.dist-info/WHEEL
uvicorn_hmr-0.1.1.8.dist-info/entry_points.txt
uvicorn_hmr.py
uvicorn_hmr-0.1.1.8.dist-info/RECORD
