Metadata-Version: 2.4
Name: uvicorn-hmr
Version: 0.1.1.8
Summary: Hot Module Reloading for Uvicorn
Keywords: uvicorn,hot-reload,hmr,reload,server
Author-Email: Muspi Merol <me@promplate.dev>
License-Expression: MIT
Classifier: Development Status :: 5 - Production/Stable
Classifier: Intended Audience :: Developers
Classifier: Operating System :: OS Independent
Project-URL: Homepage, https://github.com/promplate/hmr
Requires-Python: >=3.12
Requires-Dist: hmr~=0.7.0
Requires-Dist: typer-slim<1,>=0.15.4
Requires-Dist: uvicorn>=0.24.0
Provides-Extra: all
Requires-Dist: fastapi-reloader~=1.0; extra == "all"
